flake8_type_ignore/__init__.py
flake8_type_ignore-0.1.0.post2.dist-info/LICENSE
flake8_type_ignore-0.1.0.post2.dist-info/METADATA
flake8_type_ignore-0.1.0.post2.dist-info/WHEEL
flake8_type_ignore-0.1.0.post2.dist-info/entry_points.txt
flake8_type_ignore-0.1.0.post2.dist-info/top_level.txt
flake8_type_ignore-0.1.0.post2.dist-info/RECORD
