Metadata-Version: 2.1
Name: flake8-type-ignore
Version: 0.1.0.post2
Summary: flake8-type-ignore allows you to disallow type: ignore comments in your typed Python code.
Home-page: https://gitlab.com/jonafato/flake8-type-ignore/
Author: Jon Banafato
Author-email: pypi@jonafato.com
License: BSD 3-Clause License
Platform: UNKNOWN
Classifier: Framework :: Flake8
Classifier: Development Status :: 3 - Alpha
Classifier: Environment :: Console
Classifier: Intended Audience :: Developers
Classifier: License :: OSI Approved :: BSD License
Classifier: Programming Language :: Python
Classifier: Programming Language :: Python :: 3
Classifier: Programming Language :: Python :: 3.8
Classifier: Programming Language :: Python :: 3.9
Classifier: Topic :: Software Development :: Libraries :: Python Modules
Classifier: Topic :: Software Development :: Quality Assurance
License-File: LICENSE
